<?xml version="1.0" encoding="utf-8"?>
<odoo>
    <data>        
        <record id="crm_lead_view_form_inherit_artdeko" model="ir.ui.view">
            <field name="name">crm.lead.view.form.inherit.artdeko</field>
            <field name="model">crm.lead</field>
            <field name="inherit_id" ref="crm.crm_lead_view_form"/>
            <field name="arch" type="xml">
                <xpath expr="//button[@name='action_set_won_rainbowman']" position="before">
                    <button name="action_new_quotation_request" type="object"
                        string="Solicitar cotización" class="btn-primary"/>                    
                </xpath>              
            </field>
        </record> 
    </data>
</odoo>